test_mcp_yfei_demo/__init__.py
test_mcp_yfei_demo-0.1.2.dist-info/METADATA
test_mcp_yfei_demo-0.1.2.dist-info/WHEEL
test_mcp_yfei_demo-0.1.2.dist-info/entry_points.txt
test_mcp_yfei_demo-0.1.2.dist-info/RECORD
