Metadata-Version: 2.4
Name: test-mcp-yfei-demo
Version: 0.1.2
Summary: Add your description here
Author-email: jerry-f <easy-code@qq.com>
Requires-Python: >=3.13
Requires-Dist: mcp[cli]>=1.9.3
